{
    "ability": {
        "focus_energy": 27,
        "fury_swipes": 1,
        "karate_chop": 1,
        "leer": 1,
        "scratch": 1,
        "seismic_toss": 37,
        "thrash": 46
    },
    "ability_machine": [
        "mega_punch",
        "pay_day",
        "mega_kick",
        "body_slam",
        "take_down",
        "double_edge",
        "hyper_beam",
        "submission",
        "counter",
        "strength",
        "thunderbolt",
        "thunder",
        "dig",
        "toxic",
        "rage",
        "mimic",
        "double_team",
        "bide",
        "metronome",
        "swift",
        "skull_bash",
        "rest",
        "rock_slide",
        "substitute"
    ],
    "base_happiness": 70,
    "base_stats": {
        "attack": 105,
        "defense": 60,
        "hp": 65,
        "sp_attack": 60,
        "sp_defense": 70,
        "speed": 95
    },
    "catch_rate": 75,
    "color": "BROWN",
    "curve": "MEDIUM_FAST",
    "evolution": [],
    "female_rate": 0.5,
    "size": 1.0,
    "type": [
        "FIGHTING"
    ],
    "weight": 32.0,
    "xp_point": 159
}