{
    "ability": {
        "harden": 22,
        "hydro_pump": 47,
        "light_screen": 42,
        "minimize": 37,
        "recover": 27,
        "swift": 32,
        "tackle": 1,
        "water_gun": 17
    },
    "ability_machine": [
        "take_down",
        "double_edge",
        "surf",
        "ice_beam",
        "blizzard",
        "bubble_beam",
        "thunderbolt",
        "thunder_wave",
        "thunder",
        "toxic",
        "psychic",
        "rage",
        "teleport",
        "mimic",
        "double_team",
        "reflect",
        "bide",
        "skull_bash",
        "flash",
        "psywave",
        "rest",
        "tri_attack",
        "substitute"
    ],
    "base_happiness": 70,
    "base_stats": {
        "attack": 45,
        "defense": 55,
        "hp": 30,
        "sp_attack": 70,
        "sp_defense": 55,
        "speed": 85
    },
    "catch_rate": 225,
    "color": "BROWN",
    "curve": "SLOW",
    "evolution": [],
    "female_rate": 0.5,
    "size": 0.8,
    "type": [
        "WATER"
    ],
    "weight": 34.5,
    "xp_point": 68
}