{
    "ability": {
        "bite": 40,
        "ember": 1,
        "fire_spin": 44,
        "flamethrower": 54,
        "leer": 42,
        "quick_attack": 1,
        "rage": 48,
        "sand_attack": 1,
        "tackle": 1,
        "tail_whip": 37
    },
    "ability_machine": [
        "body_slam",
        "take_down",
        "double_edge",
        "hyper_beam",
        "toxic",
        "mimic",
        "double_team",
        "reflect",
        "bide",
        "fire_blast",
        "swift",
        "skull_bash",
        "rest",
        "substitute"
    ],
    "base_happiness": 70,
    "base_stats": {
        "attack": 130,
        "defense": 60,
        "hp": 65,
        "sp_attack": 95,
        "sp_defense": 110,
        "speed": 65
    },
    "catch_rate": 45,
    "color": "RED",
    "curve": "MEDIUM_FAST",
    "evolution": [],
    "female_rate": 0.125,
    "size": 0.9,
    "type": [
        "FIRE"
    ],
    "weight": 25.0,
    "xp_point": 184
}